{
  "modules": [
    {
  "moduleId": "Simple",
  "title": "Simple",
  "sentences": [
    { "sentenceId": "Simple_1", "english": "I like mangoes.", "transliteration": "Ja ammsho ayarum beyen" },
    { "sentenceId": "Simple_2", "english": "The monkey is on the tree.", "transliteration": "bandar tom atay bi" },
    { "sentenceId": "Simple_3", "english": "That house is big.", "transliteration": "Etay ha uyum bila" },
    { "sentenceId": "Simple_4", "english": "I am Ali.", "transliteration": "Ja Ali ba" },
    { "sentenceId": "Simple_5a", "english": "Her (right here) name is Fatima.", "transliteration": "Kinay mo muik Fatima bila" },
    { "sentenceId": "Simple_5b", "english": "Her (not here) name is Fatima.", "transliteration": "Enay mo muik Fatima bila" },
    { "sentenceId": "Simple_6", "english": "I have a headache.", "transliteration": "Ja kapal akujibi" },
    { "sentenceId": "Simple_7a", "english": "She (right here) saw a man.", "transliteration": "Kinay hir an yechumo" },
    { "sentenceId": "Simple_7b", "english": "She (not here) saw a man.", "transliteration": "Enay hir an yechumo" },
    { "sentenceId": "Simple_8a", "english": "He (right here) met a new teacher at school.", "transliteration": "Kinay school lo thosh ustaad an yenimi" },
    { "sentenceId": "Simple_8b", "english": "He (not here) met a new teacher at school.", "transliteration": "Enay school lo thosh ustaad an yenimi" },
    { "sentenceId": "Simple_9", "english": "It is raining.", "transliteration": "Halart diyarchila" },
    { "sentenceId": "Simple_10", "english": "Today is Monday.", "transliteration": "Khulto Chandura bila" },
    { "sentenceId": "Simple_11", "english": "We cooked rice in the morning.", "transliteration": "Me xhordimo bras dezeruman" },
    { "sentenceId": "Simple_12a", "english": "He (right here) saw that they are playing with a stone.", "transliteration": "Khinay uway dayo ka tamasha echumay uyazam" },
    { "sentenceId": "Simple_12b", "english": "He (not here) saw that they are playing with a stone.", "transliteration": "Enay uway dayo ka tamasha echumay uyazam" },
    { "sentenceId": "Simple_13a", "english": "She (right here) said that the woman is sleeping on the floor.", "transliteration": "Khinay senubom khinay gus chiding atay moyanubo" },
    { "sentenceId": "Simple_13b", "english": "She (not here) said that the woman is sleeping on the floor.", "transliteration": "Enay senubom khinay guy chiding atay moyanubo" },
    { "sentenceId": "Simple_14", "english": "I want to go to the town tonight.", "transliteration": "Ja khulto thampno sheher ar niyas e rai bila" },
    { "sentenceId": "Simple_15", "english": "I know that tomorrow is a holiday.", "transliteration": "Jar lali bila jimaly chuti bi" },
    { "sentenceId": "Simple_16", "english": "He (right here) tried to feed the elephant.", "transliteration": "Khiney hasto eesiras e koshish etimi" },
    { "sentenceId": "Simple_17", "english": "It was raining so I could not go to the field.", "transliteration": "Halart diyarchilum etay ganay mal ar niyas ayamanm" },
    { "sentenceId": "Simple_18", "english": "I will go when my mother comes.", "transliteration": "Beshal Ami dumomo ka j nicham" },
    { "sentenceId": "Simple_19", "english": "If it rains a lot, the plants will grow better.", "transliteration": "Butan halart diyazim ik podang shua duvashi" },
    { "sentenceId": "Simple_20", "english": "I will play with my brother.", "transliteration": "Ja axho ka khel echam" },
    { "sentenceId": "Simple_21a", "english": "She (right here) wanted to sleep early.", "transliteration": "Kinaymo xor moyanas e rai bilum" },
    { "sentenceId": "Simple_21b", "english": "She (not here) wanted to sleep early.", "transliteration": "Enaymo xor moyanas e rai bilum" },
    { "sentenceId": "Simple_22", "english": "He (right here) came to help me.", "transliteration": "Kinay ja ka zako mayar debam" },
    { "sentenceId": "Simple_23a", "english": "They (right here) are eating because they are hungry.", "transliteration": "Khuwey chaminay umanaan etay ganay shapik shichaan" },
    { "sentenceId": "Simple_23b", "english": "They (not here) are eating because they are hungry.", "transliteration": "Uway chuminay umanaan etay ganay shapik shichaan" },
    { "sentenceId": "Simple_24", "english": "We stayed inside because it was cold.", "transliteration": "Me ulay hurituman beskay holay chagrurum bilum" },
    { "sentenceId": "Simple_25", "english": "He (right here) will study after he reaches home.", "transliteration": "Kinay halar deshqlat gatami" },
    { "sentenceId": "Simple_26", "english": "I told him (not here) that she is my sister.", "transliteration": "Ja enar esam khinay ja ayasbo" },
    { "sentenceId": "Simple_27", "english": "She (right here) thinks that he (not here) will come tomorrow.", "transliteration": "Kinay samba echumbo enay jimaly xuchi" },
    { "sentenceId": "Simple_28", "english": "We waited until the bus arrived.", "transliteration": "Mu bus xush kha xat manuman" },
    { "sentenceId": "Simple_29", "english": "Although it was late, they (not here) kept working.", "transliteration": "Butn khanilum kuli k uway duro echumay hurutumn" },
    { "sentenceId": "Simple_30", "english": "I will call you if I need help.", "transliteration": "Ja gor qaw echam madad awaji manimikay" }
  ]
},
   {
  "moduleId": "Case_Markers",
  "title": "Case Markers",
  "sentences": [
    { "sentenceId": "Case_31", "english": "He (not here) kicked the ball.", "transliteration": "Enay ball dapiskı delemi" },
    { "sentenceId": "Case_32", "english": "She (right here) hit the bear.", "transliteration": "Kinay bear delumo" },
    { "sentenceId": "Case_33", "english": "The boy broke the pot.", "transliteration": "Hiles e gamla taq etimi" },
    { "sentenceId": "Case_34", "english": "She loves me.", "transliteration": "Enay mo moyarum ba" },
    { "sentenceId": "Case_35", "english": "Ayesha loves her.", "transliteration": "Enay Ayesha mo moyarum bo" },
    { "sentenceId": "Case_36", "english": "They (not here) love us.", "transliteration": "Uway me oyarum baan" },
    { "sentenceId": "Case_37", "english": "Yesterday they (not here) caught the thief.", "transliteration": "Sabur uway gey xaydunuman" },
    { "sentenceId": "Case_38", "english": "He (right here) opened the box two days back.", "transliteration": "Kinay yargunzin sandoq donam" },
    { "sentenceId": "Case_39", "english": "Ahmed gave a flower to his wife.", "transliteration": "Ahmede yous mur asqur an muchimi" },
    { "sentenceId": "Case_40", "english": "Father bought a toy for his son.", "transliteration": "You e yeh e ganay menais an yanimi" },
    { "sentenceId": "Case_41", "english": "He is working only for his family.", "transliteration": "Enay emo guti e gandy doro echai" },
    { "sentenceId": "Case_42", "english": "Give ten rupees to each one of them.", "transliteration": "kkuwayar torum rupeya ou" },
    { "sentenceId": "Case_43", "english": "She gave bread to the child.", "transliteration": "Enay giyas ar phiti youmo" },
    { "sentenceId": "Case_44", "english": "He cut the tree with an axe.", "transliteration": "Enay ghanggi atay tom churuk etimi" },
    { "sentenceId": "Case_45", "english": "She wrote with a pen.", "transliteration": "Enay pen-an atay girmunumo" },
    { "sentenceId": "Case_46", "english": "My sister is in school.", "transliteration": "Ayas school lo bo" },
    { "sentenceId": "Case_47", "english": "We are at home.", "transliteration": "Me halay baan" },
    { "sentenceId": "Case_48", "english": "He wrote the letter with a pen.", "transliteration": "Khinay pen-an atay khat girminimi" },
    { "sentenceId": "Case_49", "english": "She broke the nut with a stone.", "transliteration": "Kinay dan-an atay hani ekharumo" },
    { "sentenceId": "Case_50", "english": "We washed the clothes with soap.", "transliteration": "Me sabon atay gatong baltuman" },
    { "sentenceId": "Case_51", "english": "My sister is in school.", "transliteration": "Ayas school lo bo" },
    { "sentenceId": "Case_52", "english": "Fatima lives in Pakistan.", "transliteration": "Fatima Pakistan lo hurushubo" },
    { "sentenceId": "Case_53", "english": "Leaves are falling down from the tree.", "transliteration": "Tapong tom cum kha geyachumay bizang" },
    { "sentenceId": "Case_54", "english": "He will go to Hunza tomorrow.", "transliteration": "Enay jimaly Hunzo ar nichı" },
    { "sentenceId": "Case_55", "english": "He is in the house.", "transliteration": "Enay halay bai" },
    { "sentenceId": "Case_56", "english": "I shall go to the north tomorrow.", "transliteration": "Ja jimaly north ar nicham" },
    { "sentenceId": "Case_57", "english": "Last year it had rained in October.", "transliteration": "Thamini den a october lo halart deyarzilum" },
    { "sentenceId": "Case_58", "english": "Ali went with Ahmed.", "transliteration": "Ali Ahmed e ka nimi" },
    { "sentenceId": "Case_59", "english": "I will play with my brother.", "transliteration": "Ja acho ka khel echam" },
    { "sentenceId": "Case_60", "english": "He came with his friend.", "transliteration": "Enay emo yaran e ka demi" },
    { "sentenceId": "Case_61", "english": "My friend’s sister was ill.", "transliteration": "Ja dost e eyas bemar bom" },
    { "sentenceId": "Case_62", "english": "He cut the meat with a knife.", "transliteration": "Enay chap xuchar atay churuk etimi" },
    { "sentenceId": "Case_63", "english": "The children came from the river.", "transliteration": "Jotp sita xum duvan" },
    { "sentenceId": "Case_64", "english": "She cooked food for her brother.", "transliteration": "Khinay mocho e ganay shapik dezirumo" }
  ]
},

    {
  "moduleId": "Tense-Aspect-Mood",
  "title": "Tense-Aspect-Mood",
  "sentences": [
    { "sentenceId": "TAM_65", "english": "I am walking to field now.", "transliteration": "ja mu malar guzarchaba" },
    { "sentenceId": "TAM_66", "english": "I was walking.", "transliteration": "ja guzarchumay bayam" },
    { "sentenceId": "TAM_67", "english": "I fell down when she pushed me.", "transliteration": "Ena than atasr ja kha awalam" },
    { "sentenceId": "TAM_68", "english": "I walk to the field every day.", "transliteration": "Ja gunz mal ar guzarchaba" },
    { "sentenceId": "TAM_69", "english": "I will go to Karachi on Sunday.", "transliteration": "Ja Adit e Karachi ar nicham" },
    { "sentenceId": "TAM_70", "english": "I will not walk to school.", "transliteration": "Ja school ar akucharcham" },
    { "sentenceId": "TAM_71", "english": "I could have taken the bus if I had money.", "transliteration": "Ja lay paisa beyem k school ar bus yayamxay" },
    { "sentenceId": "TAM_72a", "english": "We are walking to the market now.", "transliteration": "Me mu bazar ar guzarchabaan" },
    { "sentenceId": "TAM_72b", "english": "We are headed to the market now.", "transliteration": "Me mu bazar ar xash baan" },
    { "sentenceId": "TAM_73", "english": "We walk to school daily.", "transliteration": "Me school ar gunz guzarchabaan" },
    { "sentenceId": "TAM_74", "english": "We could walk anywhere.", "transliteration": "Me amulur k guzaraş memayaban" },
    { "sentenceId": "TAM_75", "english": "You walk to school daily.", "transliteration": "Un school ar gunz guzarcha" },
    { "sentenceId": "TAM_76", "english": "You walked to town yesterday.", "transliteration": "Me sabur shahr ar guzaram" },
    { "sentenceId": "TAM_77", "english": "She goes to the market daily.", "transliteration": "Enay gunz bazar ar nichubo" },
    { "sentenceId": "TAM_78", "english": "She is walking very slowly now.", "transliteration": "Enay mu butn thala guzarchumay bo" },
    { "sentenceId": "TAM_79", "english": "She will walk home after sunset.", "transliteration": "Sa buur manimi k khin halar guxarchuma nicho" },
    { "sentenceId": "TAM_80", "english": "They are not walking today.", "transliteration": "Uway khulto akucharchaan" },
    { "sentenceId": "TAM_81", "english": "They walked to the river this morning.", "transliteration": "Uway khulto xordimo sinda kha guzaram" },
    { "sentenceId": "TAM_82", "english": "I might walk there later.", "transliteration": "Ja elar badany lo guzarcham" },
    { "sentenceId": "TAM_83", "english": "You should not walk at night.", "transliteration": "Un thapmo akucharas awaji" },
    { "sentenceId": "TAM_84", "english": "We will be walking when you arrive.", "transliteration": "Un dukoshqaltuma k ho mi guxarchan" },
    { "sentenceId": "TAM_85", "english": "I was not walking when you called me.", "transliteration": "Unay call etumlo ja akucharchabayam" },
    { "sentenceId": "TAM_86", "english": "We used to walk together every evening.", "transliteration": "Me gunz sabur atay gati guzarchabam" },
    { "sentenceId": "TAM_87", "english": "She has already walked to the village.", "transliteration": "enay yarnay e gawon ar guzarubo" },
    { "sentenceId": "TAM_88", "english": "They had walked far before it started raining.", "transliteration": "Uw halart deyarchas xum xor e guzaraan" },
    { "sentenceId": "TAM_89", "english": "He (not here) will have walked by the time we start.", "transliteration": "Me guzarchar dunish kha en guzarchumay maimi" },
    { "sentenceId": "TAM_90", "english": "I want to walk, but I am tired.", "transliteration": "Ja guzaras e rai bila, maghm awaraba" },
    { "sentenceId": "TAM_91", "english": "If it rains, we will walk later.", "transliteration": "Halart derazimi k me mushatay guzarchan" },
    { "sentenceId": "TAM_92", "english": "Jemal is not walking tomorrow.", "transliteration": "Ja jimalay akucharchama agayaba" },
    { "sentenceId": "TAM_93", "english": "They might have walked without us.", "transliteration": "Uway me phat nimay guzaran agayaba" }
  ]
},
    {
      "moduleId": "Negatives",
      "title": "Negatives",
      "sentences": [{ "sentenceId": "Neg_94a", "english": "He (right here) is not a teacher.", "transliteration": "Kinay ustaad apai" },
    { "sentenceId": "Neg_94b", "english": "He (not here) is not a teacher.", "transliteration": "Enay ustaad apai" },
    { "sentenceId": "Neg_94c", "english": "She (right here) is not a teacher.", "transliteration": "Kinay ustaad apo" },
    { "sentenceId": "Neg_94d", "english": "She (not here) is not a teacher.", "transliteration": "Enay ustaad apo" },
    { "sentenceId": "Neg_95", "english": "There is no water in the river.", "transliteration": "Sinda lo chil api" },
    { "sentenceId": "Neg_96", "english": "He cannot sing.", "transliteration": "Khinar er ghar etas axuchila" },
    { "sentenceId": "Neg_97", "english": "You may not go now.", "transliteration": "Un mu onichuma" },
    { "sentenceId": "Neg_98", "english": "We will not upset you.", "transliteration": "mi un biaram akochan" },
    { "sentenceId": "Neg_99", "english": "You must not move now.", "transliteration": "Muu un lan manas api" },
    { "sentenceId": "Neg_100", "english": "I didn’t eat yesterday.", "transliteration": "ja sabur bes k eshiyabayam" },
    { "sentenceId": "Neg_101", "english": "They have finished their job.", "transliteration": "Ova oymo duro fash atan" },
    { "sentenceId": "Neg_102", "english": "I have not eaten.", "transliteration": "Ja eshiyaba" },
    { "sentenceId": "Neg_103", "english": "I had not eaten yet.", "transliteration": "Ja darum eshiyaba" },
    { "sentenceId": "Neg_104", "english": "He left without informing anyone.", "transliteration": "Ena men k lail ayotumate nibai" },
    { "sentenceId": "Neg_105", "english": "They are not here.", "transliteration": "Uu kholay apan" },
    { "sentenceId": "Neg_106", "english": "I am not hungry.", "transliteration": "Jay chaminay apa" },
    { "sentenceId": "Neg_107", "english": "I do not know.", "transliteration": "Jar lail api" },
    { "sentenceId": "Neg_108", "english": "Do not enter.", "transliteration": "Ulay axu" },
    { "sentenceId": "Neg_109", "english": "I have no money.", "transliteration": "Jalay paisa apiyen" },
    { "sentenceId": "Neg_110", "english": "I did not play today.", "transliteration": "Ja khulto khel ayetabym" },
    { "sentenceId": "Neg_111", "english": "I think he will not come.", "transliteration": "En axuchi aghayaba" },
    { "sentenceId": "Neg_112", "english": "I don’t think he will come.", "transliteration": "En xuchi ayagayaba" },
    { "sentenceId": "Neg_113", "english": "I never drink juice.", "transliteration": "Ja juice omiyaba" },
    { "sentenceId": "Neg_114", "english": "She did not eat anything yesterday.", "transliteration": "Enay sabur bes k eshibom" },
    { "sentenceId": "Neg_115", "english": "I don’t see her anymore.", "transliteration": "En ar aqaishubo" },
    { "sentenceId": "Neg_116", "english": "Nothing can be done about his illness.", "transliteration": "Ena bemari ar mu beskay etas amamayaban" },
    { "sentenceId": "Neg_117", "english": "Nobody saw me.", "transliteration": "Jay menay k ayaychaan" },
    { "sentenceId": "Neg_118", "english": "Ali is nowhere in the village.", "transliteration": "Ali giram lo amlo kuli apai" },
    { "sentenceId": "Neg_119", "english": "Not even my sister believed me.", "transliteration": "Ja jaimo ayas kha etibar ayetumo" },
    { "sentenceId": "Neg_120", "english": "None of the children came.", "transliteration": "Hinkuli jurpatan atimi" },
    { "sentenceId": "Neg_121", "english": "Not everyone passed.", "transliteration": "uyon pass omanan" },
    { "sentenceId": "Neg_122", "english": "The bird is no longer on the tree.", "transliteration": "chen muto tomatay api" },
    { "sentenceId": "Neg_123", "english": "If you don’t study you will fail.", "transliteration": "Unay aqatanuma k yarqish akumaima" }]
    },
    {
      "moduleId": "Reflexive",
      "title": "Reflexive",
      "sentences": [ { "sentenceId": "Ref_124", "english": "I like myself.", "transliteration": "Ja jaimo jee ayarum bila" },
    { "sentenceId": "Ref_125", "english": "We saw ourselves in the mirror.", "transliteration": "Me mekhar shisha lo yecham" },
    { "sentenceId": "Ref_126", "english": "You cooked rice yourself.", "transliteration": "Unay bras gui dechira?" },
    { "sentenceId": "Ref_127", "english": "Maryam bought a dress for herself.", "transliteration": "Maryam e mukharar gatonik ganubom" },
    { "sentenceId": "Ref_128", "english": "Nobody loved her.", "transliteration": "En menay k oyarum apo" },
    { "sentenceId": "Ref_129", "english": "Who praises himself?", "transliteration": "Menanay ekhar dophakhurchai?" },
    { "sentenceId": "Ref_130", "english": "They told me about themselves.", "transliteration": "Uway uimo baraty jar asam." },
    { "sentenceId": "Ref_131", "english": "The door opened by itself.", "transliteration": "Hin e'ei jheng manimi" },
    { "sentenceId": "Ref_132", "english": "Muhammad and Ahmad looked at each other.", "transliteration": "Muhammad k ahmad hi'hin yakal barenuman" },
    { "sentenceId": "Ref_133", "english": "We met each other.", "transliteration": "Me hi'hin yechuman" },
    { "sentenceId": "Ref_134", "english": "They follow each other.", "transliteration": "Uu hi'hinchay echi tachan." },
    { "sentenceId": "Ref_135", "english": "She spoke to herself quietly.", "transliteration": "Enay aram ka mukharanay gharichubom" },
    { "sentenceId": "Ref_136", "english": "He hurt himself while running.", "transliteration": "Enay garchas lo ekar zaq etai" },
    { "sentenceId": "Ref_137", "english": "They defended themselves in court.", "transliteration": "Uway court lo ukhar" },
    { "sentenceId": "Ref_138", "english": "We introduced ourselves to the teacher.", "transliteration": "Me mekhar ustad ka hesh etuman" },
    { "sentenceId": "Ref_139", "english": "The cat cleaned itself.", "transliteration": "Bush e ekhar saaf etibim" },
    { "sentenceId": "Ref_140", "english": "She taught herself to read.", "transliteration": "Enay mukharay ghatanas henumo." },
    { "sentenceId": "Ref_141", "english": "He blamed himself for the mistake.", "transliteration": "Uwar ukhar imtihanay ganay tayar etuman" },
    { "sentenceId": "Ref_142", "english": "They prepared themselves for the exam.", "transliteration": "Uwar ukhar imtihanay ganay tayar etuman" },
    { "sentenceId": "Ref_143", "english": "The machine stopped by itself.", "transliteration": "Machine ei'ee xhat manimi" },
    { "sentenceId": "Ref_144", "english": "He closed the door by himself.", "transliteration": "Enay ei'ee hin ban etimi" },
    { "sentenceId": "Ref_145", "english": "We cooked dinner by ourselves.", "transliteration": "Me me'mee mekharay shapik dechiruman" },
    { "sentenceId": "Ref_146", "english": "The children dressed themselves.", "transliteration": "Jotpat e uu'uii gaton beluman" },
    { "sentenceId": "Ref_147", "english": "She protected herself from the cold.", "transliteration": "Enay chaghurum yarum mukhar bachat etumo" },
    { "sentenceId": "Ref_148", "english": "They helped each other during the storm.", "transliteration": "Uway jhurk ( snowstorm) dim'lo hi'hiney emanchay manuwam" },
    { "sentenceId": "Ref_149", "english": "We listened to each other carefully.", "transliteration": "Me hi'hin shuwa ney miltumal er'chaban" },
    { "sentenceId": "Ref_150", "english": "The two teams competed against each other.", "transliteration": "Oltik team sho e oui haran muqabila atuman" },
    { "sentenceId": "Ref_151", "english": "The birds called to each other.", "transliteration": "chiyuway ha'hanar qao echibim" },
    { "sentenceId": "Ref_152", "english": "The students shared their books with each other.", "transliteration": "Shagrdeshoway hi'hinar kitabing emasuman" },
    { "sentenceId": "Ref_153", "english": "They hugged each other and cried.", "transliteration": "Uway hi'hin bukanay netan heruman" }]
    },
    {
      "moduleId": "ECV",
      "title": "ECV",
      "sentences": [ { "sentenceId": "ECV_154", "english": "She has gone outside the house.", "transliteration": "Ena haa chum holay dusubom" },
    { "sentenceId": "ECV_155", "english": "He broke the car.", "transliteration": "Enay car kharab emanimi" },
    { "sentenceId": "ECV_156", "english": "He died.", "transliteration": "En erimi" },
    { "sentenceId": "ECV_157", "english": "She broke the engagement.", "transliteration": "Enay mangani taq etumo" },
    { "sentenceId": "ECV_158", "english": "She ran to the terrace.", "transliteration": "Enay mara teshi yakal garchumo." },
    { "sentenceId": "ECV_159", "english": "He fell down.", "transliteration": "En kha walimi" },
    { "sentenceId": "ECV_160", "english": "He cleaned up the room.", "transliteration": "Enay ee'mo kamra saaf etimi" },
    { "sentenceId": "ECV_161", "english": "She called me.", "transliteration": "Enay jar qao etumo" },
    { "sentenceId": "ECV_162", "english": "He blessed us.", "transliteration": "Enay me behel metimi." },
    { "sentenceId": "ECV_163", "english": "Go and see.", "transliteration": "Nukon baren." },
    { "sentenceId": "ECV_164", "english": "Emaan kicked me and ran away.", "transliteration": "Emaan ey jay dapiski nadil garchumo" },
    { "sentenceId": "ECV_165", "english": "Sleep after eating.", "transliteration": "Neshi gucha" },
    { "sentenceId": "ECV_166", "english": "Having eaten this food, he went to sleep.", "transliteration": "Gusay Shapik nishin en eyanimi" },
    { "sentenceId": "ECV_167", "english": "I came here to see you.", "transliteration": "Jay kholay un guyeshar dayaba" },
    { "sentenceId": "ECV_168", "english": "Hassan went to swim.", "transliteration": "Hassan tam deljar nimi" },
    { "sentenceId": "ECV_169", "english": "He came, sat, ate and went away.", "transliteration": "En deen, nuro, nishi , da nimi" },
    { "sentenceId": "ECV_170", "english": "Simra sang, danced, and entertained the guests.", "transliteration": "Simra garen ney, nukirat, osho barchy otumo" },
    { "sentenceId": "ECV_171", "english": "Finish your work and come home.", "transliteration": "Guimo duro fash ney halar xuu." },
    { "sentenceId": "ECV_172", "english": "He stood up, picked the bag, and left.", "transliteration": "En hart numa, ei'mo jola niya dusimi" },
    { "sentenceId": "ECV_173", "english": "She cooked food and served the children.", "transliteration": "Enay jotpat r shapik ney osirumo" },
    { "sentenceId": "ECV_174", "english": "They shouted and clapped.", "transliteration": "Uway qiu'piu netan kharch etuman" },
    { "sentenceId": "ECV_175", "english": "Wash your hands before eating.", "transliteration": "Shapik shiyas chum yarnay gurun balt" },
    { "sentenceId": "ECV_176", "english": "After studying, he played outside.", "transliteration": "Ghatanas chum echuwaty en nin khel etimi" },
    { "sentenceId": "ECV_177", "english": "She went to the market to buy vegetables.", "transliteration": "En bazar'r sabzi gayar nibom" },
    { "sentenceId": "ECV_178", "english": "We came to help you.", "transliteration": "Me un gumanch'e mayar demaiban" },
    { "sentenceId": "ECV_179", "english": "They sat together and talked for a long time.", "transliteration": "Uway kat nuro but khen kha chaghamin etuman" },
    { "sentenceId": "ECV_180", "english": "He looked at me and smiled.", "transliteration": "En ja ayakal barenimi da deghasimi." },
    { "sentenceId": "ECV_181", "english": "The bird flew away and disappeared.", "transliteration": "Chen duwalimi da aqanimi" },
    { "sentenceId": "ECV_182", "english": "I will go there and ask him.", "transliteration": "Jay elar nan en'chum degurusham" },
    { "sentenceId": "ECV_183", "english": "After finishing the meeting, we went home.", "transliteration": "Maraka fash netan, me halar niman." }]
    },
    {
      "moduleId": "Classifiers",
      "title": "Classifiers",
      "sentences": [  { "sentenceId": "Cls_184", "english": "My family has a goat and a chicken.", "transliteration": "Ja haa uway opachi chira'n ka qarqamuch'n bi" },
    { "sentenceId": "Cls_185", "english": "People have gathered here.", "transliteration": "Sis kholay gati manumwan" },
    { "sentenceId": "Cls_186", "english": "Dogs are barking.", "transliteration": "Hukai'e gham echiyen" },
    { "sentenceId": "Cls_187", "english": "This is a tall tree.", "transliteration": "Guty thanum thom'n bila" },
    { "sentenceId": "Cls_188", "english": "This is a wooden door.", "transliteration": "Guty hunay hin bila" },
    { "sentenceId": "Cls_189", "english": "We need an electric wire.", "transliteration": "Memar bijili'e taran awaji bi." },
    { "sentenceId": "Cls_190", "english": "This log of wood is thick.", "transliteration": "Gussay hunay sxhar daghanuman bi." },
    { "sentenceId": "Cls_191", "english": "This is a door.", "transliteration": "Guty hin bila" },
    { "sentenceId": "Cls_192", "english": "Give me a small banana.", "transliteration": "Jar jot kela'n jowa" },
    { "sentenceId": "Cls_193", "english": "I came by boat.", "transliteration": "Jay kistiyaty dayabayam" },
    { "sentenceId": "Cls_194", "english": "There is no water in the tank.", "transliteration": "Tanki lo chil api" },
    { "sentenceId": "Cls_195", "english": "We built the house with stones.", "transliteration": "Me ha dan duilan." },
    { "sentenceId": "Cls_196", "english": "Do not beat the student with a stick.", "transliteration": "Hakinasho ghache'ty odil." },
    { "sentenceId": "Cls_197", "english": "Tie them with a rope.", "transliteration": "Uway gashk'n ty uphoos." },
    { "sentenceId": "Cls_198", "english": "Go and buy some ripe fruits.", "transliteration": "Nukon kaman dughunumusho mewa uyan." },
    { "sentenceId": "Cls_199", "english": "There are two books on the table.", "transliteration": "Table ty altoh kitabchin bichan." },
    { "sentenceId": "Cls_200", "english": "The labourer needs fifty stones to build a house.", "transliteration": "Duroskuyuwar Altoh altar torumo dayo awaji biyen haa duilasay ganay." },
    { "sentenceId": "Cls_201", "english": "Give me three long objects.", "transliteration": "Jar usko ghosaiko cheezsho jowa." },
    { "sentenceId": "Cls_202", "english": "Give me one apple.", "transliteration": "Jar han baltan jowa" },
    { "sentenceId": "Cls_203", "english": "I have five cars.", "transliteration": "jalay chundo car'sho biyen" },
    { "sentenceId": "Cls_204", "english": "I need ten dresses.", "transliteration": "Jar torumo gaton awaji bichan" },
    { "sentenceId": "Cls_205", "english": "She ate four oranges.", "transliteration": "Enay walto malta shumo" },
    { "sentenceId": "Cls_206", "english": "Bring two cups of water.", "transliteration": "Altoh cupuch lo chill dusuwa" },
    { "sentenceId": "Cls_207", "english": "He bought three pieces of cloth.", "transliteration": "Enay eskikum gaton ganimi" },
    { "sentenceId": "Cls_208", "english": "We need five sheets of paper.", "transliteration": "Memar chundo kaghazing awaji bixhan" },
    { "sentenceId": "Cls_209", "english": "She picked six small stones.", "transliteration": "Enay mishindo ghoro dal otumo." },
    { "sentenceId": "Cls_210", "english": "They carried ten bags of rice.", "transliteration": "Uway torumo baras'e butuyo dal otuman" },
    { "sentenceId": "Cls_211", "english": "The shop has many kinds of flowers.", "transliteration": "Dukan ty butan zailay asqurin bixhan" },
    { "sentenceId": "Cls_212", "english": "Give me one long stick.", "transliteration": "Jar han gusanum damuwan jowa." },
    { "sentenceId": "Cls_213", "english": "He broke two glass bottles.", "transliteration": "Enay altoh sheesha botal sho ogalimi/taq otimi." }]
    },
    {
      "moduleId": "Interrogatives",
      "title": "Interrogatives",
      "sentences": [{ "sentenceId": "Int_214", "english": "What is your name?", "transliteration": "Unay guik bsn bila?" },
    { "sentenceId": "Int_215", "english": "Where are you going?", "transliteration": "Un amular nicha?" },
    { "sentenceId": "Int_216", "english": "Who is coming with you?", "transliteration": "Unay ka/ goka men xuwas ban?" },
    { "sentenceId": "Int_217", "english": "Why are you late?", "transliteration": "Un bes gukharanuma?" },
    { "sentenceId": "Int_218", "english": "When will you return?", "transliteration": "Un beshalar wapis xuchuma?" },
    { "sentenceId": "Int_219", "english": "How did you fall?", "transliteration": "Belaty guwaluma?" },
    { "sentenceId": "Int_220", "english": "Which book do you want?", "transliteration": "Unar amit khitab awaji bila??" },
    { "sentenceId": "Int_221", "english": "Whose bag is this?", "transliteration": "Gussay menay jola bi?" },
    { "sentenceId": "Int_222", "english": "Did you eat?", "transliteration": "Unay sheba?" },
    { "sentenceId": "Int_223", "english": "Can you help me?", "transliteration": "Ar amanchy manas gomaiba?" },
    { "sentenceId": "Int_224", "english": "Will he come tomorrow?", "transliteration": "En jimalay xuchi'a?" },
    { "sentenceId": "Int_225", "english": "Are they at home?", "transliteration": "Uu halay ban'a?" },
    { "sentenceId": "Int_226", "english": "Do you know her?", "transliteration": "Unay en muyena?" },
    { "sentenceId": "Int_227", "english": "What did she say?", "transliteration": "Enay bsn senumo?" },
    { "sentenceId": "Int_228", "english": "How many people are here?", "transliteration": "Kholay barum sis ban?" },
    { "sentenceId": "Int_229", "english": "Why didn’t you come yesterday?", "transliteration": "Un sabur bes atukuwam?" },
    { "sentenceId": "Int_230", "english": "Do you have money?", "transliteration": "Un gopachi rupiya biyena?" },
    { "sentenceId": "Int_231", "english": "Who are you waiting for?", "transliteration": "Unay menar intizar echa?" },
    { "sentenceId": "Int_232", "english": "Where did they go last night?", "transliteration": "Sabur thapp e uu amular nibam?" },
    { "sentenceId": "Int_233", "english": "How long will you stay here?", "transliteration": "Un beshalar kha kholay hurusha?" },
    { "sentenceId": "Int_234", "english": "What are they doing?", "transliteration": "uway bsn echan?" },
    { "sentenceId": "Int_235", "english": "Where should we meet?", "transliteration": "Me amlo dok mayan?" },
    { "sentenceId": "Int_236", "english": "Can she speak English?", "transliteration": "Enmur English garas xuchila?" },
    { "sentenceId": "Int_237", "english": "Are you feeling better now?", "transliteration": "Muto kaman shuwa ba?" },
    { "sentenceId": "Int_238", "english": "Who will help us tomorrow?", "transliteration": "Jimalay men mer xhako maiman?" },
    { "sentenceId": "Int_239", "english": "Why are they shouting?", "transliteration": "Uway bes wow echan?" },
    { "sentenceId": "Int_240", "english": "When did you see him?", "transliteration": "Unay en beshal yechuma?" },
    { "sentenceId": "Int_241", "english": "How can I solve this problem?", "transliteration": "Jey belaty guty balah chum dusham?" },
    { "sentenceId": "Int_242", "english": "Will you walk with me?", "transliteration": "Un jaka gucharchuma?" },
    { "sentenceId": "Int_243", "english": "What do you want to buy?", "transliteration": "Unay bsn yanas e rai bila?" }
  ]
    },
    {
      "moduleId": "Pronouns",
      "title": "Pronouns",
      "sentences": [{ "sentenceId": "Pro_244", "english": "I am tired.", "transliteration": "Jay awaraba." },
    { "sentenceId": "Pro_245", "english": "You are late.", "transliteration": "un gukharanuma." },
    { "sentenceId": "Pro_246", "english": "She is sleeping.", "transliteration": "En numoyan bo." },
    { "sentenceId": "Pro_247", "english": "He is standing outside.", "transliteration": "En holayakal dal diyen bai." },
    { "sentenceId": "Pro_248", "english": "They are playing.", "transliteration": "Uway khel echan." },
    { "sentenceId": "Pro_249", "english": "We will go tomorrow.", "transliteration": "Me jimalay nich'n." },
    { "sentenceId": "Pro_250", "english": "I saw them.", "transliteration": "Ja uu uyechabayam." },
    { "sentenceId": "Pro_251", "english": "She gave it to me.", "transliteration": "Enay jar gobom." },
    { "sentenceId": "Pro_252", "english": "They called you yesterday.", "transliteration": "Uwar unar sabur qao etam." },
    { "sentenceId": "Pro_253", "english": "He helped us.", "transliteration": "En mer chako manimi." },
    { "sentenceId": "Pro_254", "english": "This is my house.", "transliteration": "Guty ja haa bila." },
    { "sentenceId": "Pro_255", "english": "That is your book.", "transliteration": "Guty unay kitab bila." },
    { "sentenceId": "Pro_256", "english": "Their car is new.", "transliteration": "Uway car thosh'n bi." },
    { "sentenceId": "Pro_257", "english": "I hurt myself.", "transliteration": "Ja chot shiyam." },
    { "sentenceId": "Pro_258", "english": "They washed themselves.", "transliteration": "Uway ukhar yaltuman." },
    { "sentenceId": "Pro_259", "english": "She talked about herself.", "transliteration": "Enay muimo baraty chagha etumo." },
    { "sentenceId": "Pro_260", "english": "He brought food for them.", "transliteration": "Enay uwar shapik dichimi." },
    { "sentenceId": "Pro_261", "english": "She cut it with a knife.", "transliteration": "Enay churatay churuk etumo." },
    { "sentenceId": "Pro_262", "english": "They came from him.", "transliteration": "Uu enay ganay duwam." },
    { "sentenceId": "Pro_263", "english": "This belongs to her.", "transliteration": "Gusay inmo bi." },
    { "sentenceId": "Pro_264", "english": "This is my bag.", "transliteration": "Gusay ja jola bi." },
    { "sentenceId": "Pro_265", "english": "That is a big tree.", "transliteration": "Etay uyum toman bila." },
    { "sentenceId": "Pro_266", "english": "These are my clothes.", "transliteration": "Gukay ja gaton bixhan." },
    { "sentenceId": "Pro_267", "english": "Those are his shoes.", "transliteration": "Echay enay uuchi biyen." },
    { "sentenceId": "Pro_268", "english": "Come here.", "transliteration": "Kholar xuu." },
    { "sentenceId": "Pro_269", "english": "Go there.", "transliteration": "Elar ne." },
    { "sentenceId": "Pro_270", "english": "Put it over there.", "transliteration": "Esay elay oss." },
    { "sentenceId": "Pro_271", "english": "Leave it over there.", "transliteration": "Esay elay fath eti." },
    { "sentenceId": "Pro_272", "english": "They live near here.", "transliteration": "Uu kholay asir hurushan." },
    { "sentenceId": "Pro_273", "english": "The school is far from here.", "transliteration": "School kholum mathan bila." },
    { "sentenceId": "Pro_274", "english": "He came yesterday.", "transliteration": "En sabur debam." },
    { "sentenceId": "Pro_275", "english": "She will go tomorrow.", "transliteration": "En jimalay nicho." },
    { "sentenceId": "Pro_276", "english": "I will start now.", "transliteration": "Jay muto duyam." },
    { "sentenceId": "Pro_277", "english": "We will meet later.", "transliteration": "Me mushaty dok mayan." },
    { "sentenceId": "Pro_278", "english": "They already left.", "transliteration": "Uu chor e nibam." },
    { "sentenceId": "Pro_279", "english": "Tomorrow we will go.", "transliteration": "Jimalay me nich'n." },
    { "sentenceId": "Pro_280", "english": "Here put it.", "transliteration": "Akholar/kholar washi." }]
    },
    {
      "moduleId": "Valency",
      "title": "Valency",
      "sentences": [{ "sentenceId": "Val_281", "english": "The door opened.", "transliteration": "Hin khiren manimi." },
    { "sentenceId": "Val_282", "english": "He opened the door.", "transliteration": "Enay hin donimi." },
    { "sentenceId": "Val_283", "english": "The child woke up.", "transliteration": "Tata detalimi( for boy) / Tata dumutalumo (for girl)" },
    { "sentenceId": "Val_284", "english": "The mother woke the child up.", "transliteration": "emiye tata destalumo ( for boy) / mumiye tata dumostalumo" },
    { "sentenceId": "Val_285", "english": "The pot broke.", "transliteration": "PLACEHOLDER" },
    { "sentenceId": "Val_286", "english": "He broke the pot.", "transliteration": "PLACEHOLDER" },
    { "sentenceId": "Val_287", "english": "The food cooked.", "transliteration": "Shapik derimi." },
    { "sentenceId": "Val_288", "english": "She cooked the food.", "transliteration": "Enay shapik dechirumo." },
    { "sentenceId": "Val_289", "english": "The light turned off.", "transliteration": "Gari thami." },
    { "sentenceId": "Val_290", "english": "They turned off the light.", "transliteration": "Uway gari estaman." },
    { "sentenceId": "Val_291", "english": "The leaves fell.", "transliteration": "Tapon kha giyami." },
    { "sentenceId": "Val_292", "english": "The boy fell.", "transliteration": "Heles kha walimi" },
    { "sentenceId": "Val_293", "english": "The water boiled.", "transliteration": "Chel bapaimi." },
    { "sentenceId": "Val_294", "english": "The girl danced.", "transliteration": "Dasin giratumo." },
    { "sentenceId": "Val_295", "english": "The ice melted.", "transliteration": "Ghamu duumi." },
    { "sentenceId": "Val_296", "english": "The man ran.", "transliteration": "Hir garchimi." },
    { "sentenceId": "Val_297", "english": "He went.", "transliteration": "En nimi." },
    { "sentenceId": "Val_298", "english": "She made him go.", "transliteration": "Enay en erumo." },
    { "sentenceId": "Val_299", "english": "The baby cried.", "transliteration": "Tata hermi( boy) / Tata herumo ( Girl)" },
    { "sentenceId": "Val_300", "english": "The noise made the baby cry.", "transliteration": "Shor e tata destalimi / dumostalimi." },
    { "sentenceId": "Val_301", "english": "The fire burned.", "transliteration": "Fuu balimi." },
    { "sentenceId": "Val_302", "english": "They burned the firewood.", "transliteration": "Uway ghashil chey fuu echiman." },
    { "sentenceId": "Val_303", "english": "The boy slept.", "transliteration": "Heles eyanimi." },
    { "sentenceId": "Val_304", "english": "The teacher made the boy sit and study.", "transliteration": "Ustad e heles neurut eghatanimi." },
    { "sentenceId": "Val_305", "english": "She ate rice.", "transliteration": "Enay baras shemo." },
    { "sentenceId": "Val_306", "english": "She fed the child rice.", "transliteration": "Enay tata baras esirmo/ mosirmo." },
    { "sentenceId": "Val_307", "english": "He swam.", "transliteration": "En tam delimi." },
    { "sentenceId": "Val_308", "english": "He swam in the lake.", "transliteration": "En phari lo tham delimi." },
    { "sentenceId": "Val_309", "english": "The teacher spoke.", "transliteration": "Ustad e chagha etimi." },
    { "sentenceId": "Val_310", "english": "The teacher spoke to the class.", "transliteration": "Ustad e class ka chagha etimi." },
    { "sentenceId": "Val_311", "english": "The window opened by itself.", "transliteration": "Kirki emorati chen manimi." },
    { "sentenceId": "Val_312", "english": "He opened the window with a stick.", "transliteration": "Enay kirki damuwanaty chen etimi." },
    { "sentenceId": "Val_313", "english": "The ball rolled.", "transliteration": "Thari diri manimi." },
    { "sentenceId": "Val_314", "english": "She rolled the ball toward him.", "transliteration": "Enay thari en yakal dir etumo." }]
    },
    {
      "moduleId": "Causatives",
      "title": "Causatives",
      "sentences": [{ "sentenceId": "Cau_315", "english": "The nurse fed the baby.", "transliteration": "Nurse e tata esirumo/ mosirumo ." },
    { "sentenceId": "Cau_316", "english": "Mother made me go outside.", "transliteration": "Mama jay holnay arumo." },
    { "sentenceId": "Cau_317", "english": "I made the girl clean the room.", "transliteration": "Ja dasin kamra saaf motam." },
    { "sentenceId": "Cau_318", "english": "I made the girl clean the room with a broom.", "transliteration": "Ja dasin kamra phopos aty saaf motam." },
    { "sentenceId": "Cau_319", "english": "I made the girl ask the maid to clean the room.", "transliteration": "PLACEHOLDER" },
    { "sentenceId": "Cau_320", "english": "I made him break the glass.", "transliteration": "Ja en shisha egalam." },
    { "sentenceId": "Cau_321", "english": "Aqsa made him food.", "transliteration": "Aqsa enay ganay shapik etumo." },
    { "sentenceId": "Cau_322", "english": "The dog made the baby cry.", "transliteration": "Huk e heles ewarimi." },
    { "sentenceId": "Cau_323", "english": "The house was burnt by the thieves.", "transliteration": "Ghiyoway haa chey fuu echiman." },
    { "sentenceId": "Cau_324", "english": "Because of bad weather, we could not go to the village.", "transliteration": "PLACEHOLDER" },
    { "sentenceId": "Cau_325", "english": "The chair was broken by the children.", "transliteration": "Helesho'e kursi egalan." },
    { "sentenceId": "Cau_326", "english": "I am unable to walk.", "transliteration": "Jay gucharas ayamayaba." },
    { "sentenceId": "Cau_327", "english": "He made the child sit quietly.", "transliteration": "Enay jotpat chup no kha auwrutimi." },
    { "sentenceId": "Cau_328", "english": "They made me wait outside.", "transliteration": "Uway jay holay intizar atuman." },
    { "sentenceId": "Cau_329", "english": "She made him wash the dishes.", "transliteration": "enay en bartan eebaltumo." },
    { "sentenceId": "Cau_330", "english": "The parents made the boy study.", "transliteration": "Yu emi ey heles eghatanuman." },
    { "sentenceId": "Cau_331", "english": "He made her open the door.", "transliteration": "Enay en hin chenn motimi." },
    { "sentenceId": "Cau_332", "english": "The teacher made the students write the answer.", "transliteration": "Ustad e shagard sho jawab ogirminimi" },
    { "sentenceId": "Cau_333", "english": "The rain made the road muddy.", "transliteration": "Haralt e road tok chilgish eti bim." },
    { "sentenceId": "Cau_334", "english": "The cold weather made him sick.", "transliteration": "Chaghurum'e en bemar etimi." },
    { "sentenceId": "Cau_335", "english": "The loud noise made the birds fly away.", "transliteration": "lawoo paoo manasar cheyo dulwalimiyen." },
    { "sentenceId": "Cau_336", "english": "The wind made the trees fall.", "transliteration": "Tesh e thom kha bishami." },
    { "sentenceId": "Cau_337", "english": "The doctor made me take medicine.", "transliteration": "PLACEHOLDER" },
    { "sentenceId": "Cau_338", "english": "She made them tell the truth.", "transliteration": "Enay chanay ogharumo." },
    { "sentenceId": "Cau_339", "english": "We made him carry the bags.", "transliteration": "Mee en jolamuxh eyanuman." },
    { "sentenceId": "Cau_340", "english": "They made her clean the house.", "transliteration": "Uway en haa saaf motuman." },
    { "sentenceId": "Cau_341", "english": "The heat made the ice melt.", "transliteration": "Gharurum'e ghamu destumi." },
    { "sentenceId": "Cau_342", "english": "The smell made me feel sick.", "transliteration": "Nass e jay beyaye awashimi." },
    { "sentenceId": "Cau_343", "english": "The joke made everyone laugh.", "transliteration": "Masqara uyon oghasimi." },
    { "sentenceId": "Cau_344", "english": "The teacher made them read the story again.", "transliteration": "Ustad e uu minas dobara osanimi." }]
    },
    {
      "moduleId": "Interrogatives_(2)",
      "title": "Interrogatives (2)",
      "sentences": [{ "sentenceId": "Int_345", "english": "What are you doing?", "transliteration": "Unay bsn echa?" },
    { "sentenceId": "Int_346", "english": "Where did they go?", "transliteration": "Uu amular niban?" },
    { "sentenceId": "Int_347", "english": "Who came yesterday?", "transliteration": "Sabur men duwam?" },
    { "sentenceId": "Int_348", "english": "When will she arrive?", "transliteration": "En beshalar xuwas bo/ xuxho?" },
    { "sentenceId": "Int_349", "english": "Why are you crying?", "transliteration": "Un bes hercha?" },
    { "sentenceId": "Int_350", "english": "How did he fix it?", "transliteration": "Enay belaty warxh etimi?" },
    { "sentenceId": "Int_351", "english": "Did they finish the work?", "transliteration": "Uway duro fash etumana?" },
    { "sentenceId": "Int_352", "english": "Will she stay here?", "transliteration": "En kholay hurutas bowa/ hurushubowa?" },
    { "sentenceId": "Int_353", "english": "Do you trust him?", "transliteration": "Unay enaty atibar echa?" },
    { "sentenceId": "Int_354", "english": "Are you feeling better now?", "transliteration": "Mu shuwa/thik ba un?" },
    { "sentenceId": "Int_355", "english": "Did it rain last night?", "transliteration": "Sabur Haralt diyarchiluma?" },
    { "sentenceId": "Int_356", "english": "What did he break?", "transliteration": "Enay beshal egalimi?" },
    { "sentenceId": "Int_357", "english": "Who did you call?", "transliteration": "Unay menar qao eta?" },
    { "sentenceId": "Int_358", "english": "What are they looking at?", "transliteration": "Uway bsn yakal baraiban?" },
    { "sentenceId": "Int_359", "english": "Whom did she meet there?", "transliteration": "Elay en menay ka dok manubom?" },
    { "sentenceId": "Int_360", "english": "Who gave you money?", "transliteration": "Unar menay rupiya guwan?" },
    { "sentenceId": "Int_361", "english": "What are they doing with the knife?", "transliteration": "Uway chur'e ka bsn echan?" },
    { "sentenceId": "Int_362", "english": "Where did she come from?", "transliteration": "En amlum dumobom?" },
    { "sentenceId": "Int_363", "english": "Who are you going with?", "transliteration": "Un menay ka niyas ba?" },
    { "sentenceId": "Int_364", "english": "Where did he put the books?", "transliteration": "Enay kitabchen amlo aeurutai?" },
    { "sentenceId": "Int_365", "english": "Do you have a headache?", "transliteration": "Unay kapal gokholjibiya?" },
    { "sentenceId": "Int_366", "english": "Whose child is this?", "transliteration": "khinay tata menay bai?" },
    { "sentenceId": "Int_367", "english": "Do they have enough food?", "transliteration": "Uualay shapik biya?" },
    { "sentenceId": "Int_368", "english": "Can she read this?", "transliteration": "Enay gutay ghatanas momaibowa?" },
    { "sentenceId": "Int_369", "english": "Should we go now?", "transliteration": "Me muu nichana?" },
    { "sentenceId": "Int_370", "english": "May I open the door?", "transliteration": "Hing siqa echama?" },
    { "sentenceId": "Int_371", "english": "Why didn’t you tell me?", "transliteration": "Unay jar bes ayasam?" },
    { "sentenceId": "Int_372", "english": "Did he not see them?", "transliteration": "Enay uu oiche'a?" },
    { "sentenceId": "Int_373", "english": "Don’t they know the truth?", "transliteration": "Uwar chan lail apiya?" },
    { "sentenceId": "Int_374", "english": "How many children came today?", "transliteration": "Khulto berum jotpat duwan?" },
    { "sentenceId": "Int_375", "english": "Where did he go?", "transliteration": "En amular nimi?" }]
    },
    {
      "moduleId": "Possession",
      "title": "Possession",
      "sentences": [{ "sentenceId": "Pos_376", "english": "I have a book.", "transliteration": "Jalay kitab bila." },
    { "sentenceId": "Pos_377", "english": "She has a new phone.", "transliteration": "Enmulay tosh phone'n bi." },
    { "sentenceId": "Pos_378", "english": "They have a car.", "transliteration": "Uwalay car'n bi./ Uu opachi car'n bi." },
    { "sentenceId": "Pos_379", "english": "He has a house in the village.", "transliteration": "Enay giram lo haa bila." },
    { "sentenceId": "Pos_380", "english": "We have three goats.", "transliteration": "Memalay usko cheersho biyen" },
    { "sentenceId": "Pos_381", "english": "She has a daughter.", "transliteration": "Enmo moyan bo." },
    { "sentenceId": "Pos_382", "english": "He has two brothers.", "transliteration": "Enay altan echokon ban." },
    { "sentenceId": "Pos_383", "english": "My family has land near the river.", "transliteration": "Ja family e sinda epachi buxhai bila." },
    { "sentenceId": "Pos_384", "english": "They have no money.", "transliteration": "Uwalay rupiya apiyen." },
    { "sentenceId": "Pos_385", "english": "I have some time today.", "transliteration": "Jalay khulto kamn khain bila." },
    { "sentenceId": "Pos_386", "english": "She has a headache.", "transliteration": "Enmo kapal mukholjibi." },
    { "sentenceId": "Pos_387", "english": "I have an illness.", "transliteration": "Jay beyaye nawal ba." },
    { "sentenceId": "Pos_388", "english": "He has fever.", "transliteration": "Enchay tataghar bila." },
    { "sentenceId": "Pos_389", "english": "We have hope.", "transliteration": "Me umeed bila." },
    { "sentenceId": "Pos_390", "english": "They have a plan.", "transliteration": "Uu opachi shuwa tarqeeb n bila." },
    { "sentenceId": "Pos_391", "english": "She has good ideas.", "transliteration": "En mopachi shuwa khayal'n bichan." },
    { "sentenceId": "Pos_392", "english": "The school has many teachers.", "transliteration": "School lo butan ustadesho ban." },
    { "sentenceId": "Pos_393", "english": "The house has a small garden.", "transliteration": "Haa ka jot basiyan bila." },
    { "sentenceId": "Pos_394", "english": "The bag has five pockets.", "transliteration": "Jola chundo chamdamuxh biyen." },
    { "sentenceId": "Pos_395", "english": "The tree has long branches.", "transliteration": "Tomay gusaikaro sxharanch biyen." },
    { "sentenceId": "Pos_396", "english": "Our village has a small clinic.", "transliteration": "Me giram ulo jot clinic'n bila." },
    { "sentenceId": "Pos_397", "english": "Their shop has fresh bread.", "transliteration": "Uway dukan ty thosh phiti'n bi." },
    { "sentenceId": "Pos_398", "english": "The river has clear water.", "transliteration": "Sindawlo saaf chel bila." },
    { "sentenceId": "Pos_399", "english": "The classroom has big windows.", "transliteration": "Class lo uyonko kirkimin bixhan." },
    { "sentenceId": "Pos_400", "english": "The city has many parks.", "transliteration": "Shahar ulo butan karmayar basimin bixhan." },
    { "sentenceId": "Pos_401", "english": "My brother has a bicycle.", "transliteration": "Ja acho epachi cycle n bi." },
    { "sentenceId": "Pos_402", "english": "Her child has a toy.", "transliteration": "PLACEHOLDER" },
    { "sentenceId": "Pos_403", "english": "The farmer has two cows.", "transliteration": "PLACEHOLDER" },
    { "sentenceId": "Pos_404", "english": "I have work to do today.", "transliteration": "PLACEHOLDER" },
    { "sentenceId": "Pos_405", "english": "They have everything they need.", "transliteration": "PLACEHOLDER" }]

    },
    {
      "moduleId": "Adpositions-postpositions",
      "title": "Adpositions-postpositions",
      "sentences": [ { "sentenceId": "Adp_406", "english": "I am at home.", "transliteration": "Ja haley ba." },
    { "sentenceId": "Adp_407", "english": "She is in the room.", "transliteration": "Mo muya kutu uly bu." },
    { "sentenceId": "Adp_408", "english": "They are on the roof.", "transliteration": "Wey sholth yatey ban." },
    { "sentenceId": "Adp_409", "english": "The dog is under the table.", "transliteration": "Huk table yaty bi." },
    { "sentenceId": "Adp_410", "english": "The book is on the chair.", "transliteration": "Kitab sandali yarey dua." },
    { "sentenceId": "Adp_411", "english": "We are behind the house.", "transliteration": "Me hah elgeken ban." },
    { "sentenceId": "Adp_412", "english": "Put the bag on the table.", "transliteration": "Bokhcha table yty oss." },
    { "sentenceId": "Adp_413", "english": "Put the shoes near the door.", "transliteration": "Tawching hing a asur oss." },
    { "sentenceId": "Adp_414", "english": "The children are inside the school.", "transliteration": "Dulashu school e ulikal ban." },
    { "sentenceId": "Adp_415", "english": "The key is inside the box.", "transliteration": "Tal sandog a ulikal bi." },
    { "sentenceId": "Adp_416", "english": "He is standing outside the gate.", "transliteration": "Ney dambar a holikal deyam bai." },
    { "sentenceId": "Adp_417", "english": "They are sitting beside me.", "transliteration": "Wey ja aphatki hurachaman." },
    { "sentenceId": "Adp_418", "english": "She walked to the river.", "transliteration": "Mo sandey khash gucharu." },
    { "sentenceId": "Adp_419", "english": "He ran to the house.", "transliteration": "Ne hala huwey." },
    { "sentenceId": "Adp_420", "english": "They went to the market.", "transliteration": "Wey bazar a galen." },
    { "sentenceId": "Adp_421", "english": "She came from the mountain.", "transliteration": "Mo charku um domom bu." },
    { "sentenceId": "Adp_422", "english": "He fell from the tree.", "transliteration": "Ney nosh tamu khat wali." },
    { "sentenceId": "Adp_423", "english": "The water flows from the pipe.", "transliteration": "Chel pipe ghang gucharchun dua." },
    { "sentenceId": "Adp_424", "english": "She arrived from the city.", "transliteration": "Mo shahar um dis manu." },
    { "sentenceId": "Adp_425", "english": "I will go with my friend.", "transliteration": "Ja aya yaram ka chram." },
    { "sentenceId": "Adp_426", "english": "He cut the fruit with a knife.", "transliteration": "Ne mewa tesh yty tar ati." },
    { "sentenceId": "Adp_427", "english": "She swept the floor with a broom.", "transliteration": "Mp phopos yatey bend khash atu." },
    { "sentenceId": "Adp_428", "english": "They built the wall with stones.", "transliteration": "Wey ghoro yatey bal doyeh en." },
    { "sentenceId": "Adp_429", "english": "The school is far from here.", "transliteration": "School akholum mathan dua." },
    { "sentenceId": "Adp_430", "english": "She stood between the two boys.", "transliteration": "Mo altan dulashu makuche deyuh." },
    { "sentenceId": "Adp_431", "english": "We walked through the forest.", "transliteration": "Me mushk harangtal gucharen." },
    { "sentenceId": "Adp_432", "english": "The bus stopped near the bridge.", "transliteration": "Bus mashk apai destayen." },
    { "sentenceId": "Adp_433", "english": "The store is across the road.", "transliteration": "Jinari mo osas kutu gun a et yakal bi." },
    { "sentenceId": "Adp_434", "english": "The teacher stood in front of the class.", "transliteration": "Ustad gati engi deeyai." },
    { "sentenceId": "Adp_435", "english": "He put the cup on top of the shelf.", "transliteration": "Ney phul hashtik thanish osi." }]
    },
    {
      "moduleId": "Passive",
      "title": "Passive",
      "sentences": [{ "sentenceId": "Pas_436", "english": "The door was opened.", "transliteration": "Hing dohonen." },
    { "sentenceId": "Pas_437", "english": "The door was opened by the boy.", "transliteration": "Hing hales en a dohunuman." },
    { "sentenceId": "Pas_438", "english": "The food was cooked.", "transliteration": "Paqo destarumam." },
    { "sentenceId": "Pas_439", "english": "The food was cooked by her.", "transliteration": "Paqo mo destarumum." },
    { "sentenceId": "Pas_440", "english": "The house was built last year.", "transliteration": "Hah thameney doyum am." },
    { "sentenceId": "Pas_441", "english": "The house was built by them.", "transliteration": "Hah wey doyum am." },
    { "sentenceId": "Pas_442", "english": "The letter was written.", "transliteration": "Khat girminen." },
    { "sentenceId": "Pas_443", "english": "The letter was written by my brother.", "transliteration": "Khat ja ache dawaqal agriminum am." },
    { "sentenceId": "Pas_444", "english": "The car was repaired yesterday.", "transliteration": "Car satik watch eten." },
    { "sentenceId": "Pas_445", "english": "The road was cleaned by the workers.", "transliteration": "Gun droskuyu khash eten." },
    { "sentenceId": "Pas_446", "english": "The glass was broken.", "transliteration": "Glass galum bim." },
    { "sentenceId": "Pas_447", "english": "The glass was broken by the child.", "transliteration": "Glass dulus a galumam." },
    { "sentenceId": "Pas_448", "english": "The rice will be cooked.", "transliteration": "Grinj destarchamen." },
    { "sentenceId": "Pas_449", "english": "The room will be cleaned soon.", "transliteration": "Kutu shuw khash echemnen." },
    { "sentenceId": "Pas_450", "english": "The work will be finished by tomorrow.", "transliteration": "Dro jimal khash khul myeme." },
    { "sentenceId": "Pas_451", "english": "The tree was cut down by the men.", "transliteration": "Nosh hir a khata deli." },
    { "sentenceId": "Pas_452", "english": "The girl was taught by her mother.", "transliteration": "Dasen mo ga moseni." },
    { "sentenceId": "Pas_453", "english": "Many people were helped.", "transliteration": "But ses a uren deshqati." },
    { "sentenceId": "Pas_454", "english": "The children were fed.", "transliteration": "Dulashu ga osaren." },
    { "sentenceId": "Pas_455", "english": "The baby was carried.", "transliteration": "Echogon dulus dal net chuyen." },
    { "sentenceId": "Pas_456", "english": "The books were taken from the shelf.", "transliteration": "Kitabecing balkash um yanumam." },
    { "sentenceId": "Pas_457", "english": "The door will be painted tomorrow.", "transliteration": "Hing a jimal roghan maltarchamen." },
    { "sentenceId": "Pas_458", "english": "The plan was changed at the last minute.", "transliteration": "Akhri khain uly dunesh far eten." },
    { "sentenceId": "Pas_459", "english": "The gifts were given to the children.", "transliteration": "Dulashu harang hayau faken." },
    { "sentenceId": "Pas_460", "english": "The meeting was canceled.", "transliteration": "Mahraka bey eten." },
    { "sentenceId": "Pas_461", "english": "The rules must be followed.", "transliteration": "Chan baring yatey gucharchum bash." },
    { "sentenceId": "Pas_462", "english": "The thief was caught by the police.", "transliteration": "Police a ghaing harken." },
    { "sentenceId": "Pas_463", "english": "The vegetables are washed before cooking.", "transliteration": "Hoi destarchum yr halchachuman." },
    { "sentenceId": "Pas_464", "english": "The bridge was destroyed by the flood.", "transliteration": "Bashk mos a turzutuzru atumbi." },
    { "sentenceId": "Pas_465", "english": "The story was told by the teacher.", "transliteration": "Menes ustad a ati." }]
    },
    {
      "moduleId": "Imperatives",
      "title": "Imperatives",
      "sentences": [ { "sentenceId": "Imp_466", "english": "Come here.", "transliteration": "Khola jo." },
    { "sentenceId": "Imp_467", "english": "Go there.", "transliteration": "Tola ney." },
    { "sentenceId": "Imp_468", "english": "Sit down.", "transliteration": "Yarey hurut." },
    { "sentenceId": "Imp_469", "english": "Stand up.", "transliteration": "Dal deeyeh." },
    { "sentenceId": "Imp_470", "english": "Listen to me.", "transliteration": "Jaga gutumal et." },
    { "sentenceId": "Imp_471", "english": "Look at me.", "transliteration": "Ja ayakala ghan." },
    { "sentenceId": "Imp_472", "english": "Read this.", "transliteration": "Gutry sen." },
    { "sentenceId": "Imp_473", "english": "Write your name.", "transliteration": "Guya guyek girmin." },
    { "sentenceId": "Imp_474", "english": "Open the door.", "transliteration": "Hing dohon." },
    { "sentenceId": "Imp_475", "english": "Close the window.", "transliteration": "Balkash dohon." },
    { "sentenceId": "Imp_476", "english": "Bring water.", "transliteration": "Chel duchu." },
    { "sentenceId": "Imp_477", "english": "Give me that book.", "transliteration": "Tey kitab ache a." },
    { "sentenceId": "Imp_478", "english": "Help me.", "transliteration": "Jaga guren achi." },
    { "sentenceId": "Imp_479", "english": "Wait here.", "transliteration": "Akho athen." },
    { "sentenceId": "Imp_480", "english": "Speak slowly.", "transliteration": "Bilash baring et." },
    { "sentenceId": "Imp_481", "english": "Do not go there.", "transliteration": "Tola ayeney." },
    { "sentenceId": "Imp_482", "english": "Do not touch that.", "transliteration": "Sey chey dohon bey." },
    { "sentenceId": "Imp_483", "english": "Do not speak loudly.", "transliteration": "Dol baring ayet." },
    { "sentenceId": "Imp_484", "english": "Do not run inside.", "transliteration": "Ulikal huweas api." },
    { "sentenceId": "Imp_485", "english": "Do not open the door.", "transliteration": "Hing dohon bey." },
    { "sentenceId": "Imp_486", "english": "Go and bring milk.", "transliteration": "Noko manu duchu." },
    { "sentenceId": "Imp_487", "english": "Sit and listen.", "transliteration": "Nuhurut gutumal et." },
    { "sentenceId": "Imp_488", "english": "Come and help me.", "transliteration": "Doko kamen guren dames jaga." },
    { "sentenceId": "Imp_489", "english": "Eat and sleep.", "transliteration": "Neeshi gucha." },
    { "sentenceId": "Imp_490", "english": "Wash your hands before eating.", "transliteration": "Shechum chum yr guren halacha." },
    { "sentenceId": "Imp_491", "english": "Please wait a moment.", "transliteration": "Hek darbat athen ka." },
    { "sentenceId": "Imp_492", "english": "Please help the children.", "transliteration": "Dulashu ga guren demasa." },
    { "sentenceId": "Imp_493", "english": "Let them come inside.", "transliteration": "Ney ulikal a chura fat et." },
    { "sentenceId": "Imp_494", "english": "Let them speak.", "transliteration": "Wey baring acha fat ot." },
    { "sentenceId": "Imp_495", "english": "Let her sit here.", "transliteration": "Mo akho nutrusha fat mot." },
    { "sentenceId": "Imp_496", "english": "Bring the children inside.", "transliteration": "Dulashu khulikal a duche." },
    { "sentenceId": "Imp_497", "english": "Stop talking and listen.", "transliteration": "Baring achum yah net gutumal et." },
    { "sentenceId": "Imp_498", "english": "Leave the bag on the table.", "transliteration": "Bokhcha table yty fat et." },
    { "sentenceId": "Imp_499", "english": "Keep the door open.", "transliteration": "Hing dohon ya fat et." },
    { "sentenceId": "Imp_500", "english": "Bring me your notes tomorrow.", "transliteration": "Jimal guya girminumang jaga duchu." }]
    }
  ]
}
